{
  "$schema": "https://developer.microsoft.com/json-schemas/fabric/item/report/definition/visualContainer/2.7.0/schema.json",
  "name": "add5d99ba2e27ab3b078",
  "position": {
    "x": 450.14547754585709,
    "y": 179.73434535104366,
    "z": 8,
    "height": 518.15306767868435,
    "width": 830.664136622391,
    "tabOrder": 3000
  },
  "visual": {
    "visualType": "lineChart",
    "query": {
      "queryState": {
        "Category": {
          "projections": [
            {
              "field": {
                "Column": {
                  "Expression": {
                    "SourceRef": {
                      "Entity": "vw_Dim_FiscalMonth"
                    }
                  },
                  "Property": "Fiscal Quarter"
                }
              },
              "queryRef": "vw_Dim_FiscalMonth.Fiscal Quarter",
              "nativeQueryRef": "Fiscal Quarter",
              "active": true
            }
          ]
        },
        "Series": {
          "projections": []
        },
        "Y": {
          "projections": [
            {
              "field": {
                "Aggregation": {
                  "Expression": {
                    "Column": {
                      "Expression": {
                        "SourceRef": {
                          "Entity": "vw_SalesFigures_All"
                        }
                      },
                      "Property": "Value"
                    }
                  },
                  "Function": 0
                }
              },
              "queryRef": "Sum(vw_SalesFigures_All.Value)",
              "nativeQueryRef": "Sum of Value"
            }
          ]
        }
      },
      "sortDefinition": {
        "sort": [
          {
            "field": {
              "Column": {
                "Expression": {
                  "SourceRef": {
                    "Entity": "vw_Dim_FiscalMonth"
                  }
                },
                "Property": "Fiscal Quarter"
              }
            },
            "direction": "Ascending"
          }
        ]
      }
    },
    "visualContainerObjects": {
      "title": [
        {
          "properties": {
            "text": {
              "expr": {
                "Literal": {
                  "Value": "'Sales Trend by Quarter'"
                }
              }
            }
          }
        }
      ]
    },
    "drillFilterOtherVisuals": true
  },
  "filterConfig": {
    "filters": [
      {
        "name": "a83593950581e16cfa43",
        "field": {
          "Aggregation": {
            "Expression": {
              "Column": {
                "Expression": {
                  "SourceRef": {
                    "Entity": "vw_SalesFigures_All"
                  }
                },
                "Property": "Value"
              }
            },
            "Function": 0
          }
        },
        "type": "Advanced"
      },
      {
        "name": "7c6a6a338af1223f590a",
        "field": {
          "Column": {
            "Expression": {
              "SourceRef": {
                "Entity": "vw_Dim_FiscalMonth"
              }
            },
            "Property": "Fiscal Quarter"
          }
        },
        "type": "Categorical"
      }
    ]
  }
}